MANIFEST.in
README.md
requirements.txt
setup.cfg
setup.py
pybbn/__init__.py
pybbn.egg-info/PKG-INFO
pybbn.egg-info/SOURCES.txt
pybbn.egg-info/dependency_links.txt
pybbn.egg-info/requires.txt
pybbn.egg-info/top_level.txt
pybbn/causality/__init__.py
pybbn/causality/ace.py
pybbn/gaussian/__init__.py
pybbn/gaussian/inference.py
pybbn/generator/__init__.py
pybbn/generator/bbngenerator.py
pybbn/graph/__init__.py
pybbn/graph/dag.py
pybbn/graph/edge.py
pybbn/graph/factory.py
pybbn/graph/graph.py
pybbn/graph/jointree.py
pybbn/graph/node.py
pybbn/graph/pdag.py
pybbn/graph/potential.py
pybbn/graph/util.py
pybbn/graph/variable.py
pybbn/pptc/__init__.py
pybbn/pptc/evidencecollector.py
pybbn/pptc/evidencedistributor.py
pybbn/pptc/inferencecontroller.py
pybbn/pptc/initializer.py
pybbn/pptc/moralizer.py
pybbn/pptc/potentialinitializer.py
pybbn/pptc/propagator.py
pybbn/pptc/transformer.py
pybbn/pptc/triangulator.py
pybbn/sampling/__init__.py
pybbn/sampling/sampling.py