Metadata-Version: 2.1
Name: pybbn
Version: 3.2.1
Summary: Learning and Inference in Bayesian Belief Networks
Home-page: https://github.com/vangj/py-bbn
Author: Jee Vang
Author-email: vangjee@gmail.com
License: UNKNOWN
Keywords: bayesian belief network exact approximate inference junction tree algorithm pptc dag gibbs sampling multivariate conditional gaussian linear causal causality structure parameter causal causality
Platform: UNKNOWN
Classifier: Programming Language :: Python :: 3
Classifier: License :: OSI Approved :: Apache Software License
Classifier: Operating System :: OS Independent
Classifier: Topic :: Scientific/Engineering :: Artificial Intelligence
Classifier: Intended Audience :: Developers
Classifier: Intended Audience :: Science/Research
Classifier: Development Status :: 5 - Production/Stable
